MANIFEST.in
setup.cfg
setup.py
duckpond/__init__.py
duckpond.egg-info/PKG-INFO
duckpond.egg-info/SOURCES.txt
duckpond.egg-info/dependency_links.txt
duckpond.egg-info/requires.txt
duckpond.egg-info/top_level.txt
duckpond/apps/__init__.py
duckpond/apps/blog/__init__.py
duckpond/apps/blog/__main__.py
duckpond/apps/blog/app.py
duckpond/apps/blog/views.py
duckpond/apps/blog/assets/css/media.css
duckpond/apps/blog/assets/css/print.css
duckpond/apps/blog/assets/css/style.css
duckpond/apps/blog/templates/base.html
duckpond/apps/blog/templates/content.html
duckpond/apps/blog/templates/error.html
duckpond/apps/blog/templates/keyword.html
duckpond/apps/editor/__init__.py
duckpond/apps/editor/__main__.py
duckpond/apps/editor/api.py
duckpond/apps/editor/app.py
duckpond/apps/editor/assets.py
duckpond/apps/editor/forms.py
duckpond/apps/editor/model.py
duckpond/apps/editor/views.py
duckpond/apps/editor/assets/content/editor.html
duckpond/apps/editor/assets/css/editor.css
duckpond/apps/editor/assets/css/html-editor.css
duckpond/apps/editor/assets/css/uikit.min.css
duckpond/apps/editor/assets/images/accordion-close.svg
duckpond/apps/editor/assets/images/accordion-open.svg
duckpond/apps/editor/assets/images/close-large.svg
duckpond/apps/editor/assets/images/close.svg
duckpond/apps/editor/assets/images/divider-icon.svg
duckpond/apps/editor/assets/images/form-checkbox-indeterminate.svg
duckpond/apps/editor/assets/images/form-checkbox.svg
duckpond/apps/editor/assets/images/form-radio.svg
duckpond/apps/editor/assets/images/form-select.svg
duckpond/apps/editor/assets/images/icons.svg
duckpond/apps/editor/assets/images/list-bullet.svg
duckpond/apps/editor/assets/images/nav-parent-close.svg
duckpond/apps/editor/assets/images/nav-parent-open.svg
duckpond/apps/editor/assets/images/navbar-toggle.svg
duckpond/apps/editor/assets/images/overlay.svg
duckpond/apps/editor/assets/images/pagination-next.svg
duckpond/apps/editor/assets/images/pagination-previous.svg
duckpond/apps/editor/assets/images/search-default.svg
duckpond/apps/editor/assets/images/search-large.svg
duckpond/apps/editor/assets/images/search-navbar.svg
