Metadata-Version: 1.1
Name: duckpond
Version: 0.10.4
Summary: A semantic pond for content delivery
Home-page: https://github.com/alexmilowski/duckpond
Author: Alex Miłowski
Author-email: alex@milowski.com
License: Apache 2.0
Keywords: sparql semantics cms
Platform: UNKNOWN
Classifier: Development Status :: 4 - Beta
Classifier: Intended Audience :: Developers
Classifier: Topic :: Software Development :: Libraries
Classifier: License :: OSI Approved :: Apache Software License
Classifier: Programming Language :: Python :: 3
Classifier: Programming Language :: Python :: 3.3
Classifier: Programming Language :: Python :: 3.4
Classifier: Programming Language :: Python :: 3.5
